.gitignore
LICENSE
README.md
noxfile.py
requirements.txt
sanka.py
setup.py
test_sanka.py
.github/workflows/publish.yaml
.github/workflows/tests.yaml
examples/actionpack/Dockerfile
examples/actionpack/example.py
examples/actionpack/requirements.txt
sanka.egg-info/PKG-INFO
sanka.egg-info/SOURCES.txt
sanka.egg-info/dependency_links.txt
sanka.egg-info/top_level.txt